[
  {
    "title": "Ofir",
    "from": "Bar",
    "content": "contentcontentcontentcontentcontentcontentcontentcontent",
    "date": 1590564794000,
    "favorite": true,
    "new": false,
    "position": "outbox"
  },
  {
    "title": "try",
    "from": "Bar",
    "content": "qwegfwrgrg",
    "date": 1592564894000,
    "favorite": false,
    "new": false,
    "position": "outbox"
  },
  {
    "title": "aer",
    "from": "5tg",
    "content": "sergrttt",
    "date": 1590564894000,
    "favorite": true,
    "new": false,
    "position": "outbox"
  },
  {
    "title": "Ofir",
    "from": "Bar",
    "content": "contentcontentcontentcontentcontentcontentcontentcontent",
    "date": 1590564795000,
    "favorite": false,
    "new": false,
    "position": "outbox"
  },
  {
    "title": "Ofir",
    "from": "Bar",
    "content": "contentcontentcontentcontentcontentcontentcontentcontent",
    "date": 1590564796000,
    "favorite": false,
    "new": false,
    "position": "outbox"
  },
  {
    "title": "Ofir",
    "from": "Bar",
    "content": "contentcontentcontentcontentcontentcontentcontentcontent",
    "date": 1590564797000,
    "favorite": false,
    "new": false,
    "position": "outbox"
  },
  {
    "title": "Ofir",
    "from": "Bar",
    "content": "contentcontentcontentcontentcontentcontentcontentcontent",
    "date": 1590564790000,
    "favorite": false,
    "new": false,
    "position": "outbox"
  },
  {
    "title": "Ofir",
    "from": "Bar",
    "content": "contentcontentcontentcontentcontentcontentcontentcontent",
    "date": 1590564794200,
    "favorite": false,
    "new": false,
    "position": "outbox"
  },
  {
    "title": "Ofir",
    "from": "Bar",
    "content": "contentcontentcontentcontentcontentcontentcontentcontent",
    "date": 1590564795000,
    "favorite": false,
    "new": false,
    "position": "outbox"
  },
  {
    "title": "Ofir",
    "from": "Bar",
    "content": "contentcontentcontentcontentcontentcontentcontentcontent",
    "date": 1590564794000,
    "favorite": false,
    "new": false,
    "position": "outbox"
  },
  {
    "title": "Ofir",
    "from": "Bar",
    "content": "contentcontentcontentcontentcontentcontentcontentcontent",
    "date": 1590565784000,
    "favorite": false,
    "new": false,
    "position": "outbox"
  },
  {
    "title": "Ofir",
    "from": "Bar",
    "content": "contentcontentcontentcontentcontentcontentcontentcontent",
    "date": 1590564794000,
    "favorite": false,
    "new": false,
    "position": "outbox"
  }
]